karabo_hdf5writer/__init__.py
karabo_hdf5writer/_version.py
karabo_hdf5writer/hdf5writer.py
karabo_hdf5writer/scene.py
karabo_hdf5writer/tests/__init__.py
karabo_hdf5writer/tests/property_naming_test.py
karabo_hdf5writer/tests/sub_module_test.py
karabo_hdf5writer/tests/test_acquisition.py
karabo_hdf5writer/tests/test_configuration.py
karabo_hdf5writer-3.0.1.dist-info/licenses/LICENSE.md
karabo_hdf5writer-3.0.1.dist-info/METADATA
karabo_hdf5writer-3.0.1.dist-info/WHEEL
karabo_hdf5writer-3.0.1.dist-info/entry_points.txt
karabo_hdf5writer-3.0.1.dist-info/top_level.txt
karabo_hdf5writer-3.0.1.dist-info/RECORD
