Metadata-Version: 2.4
Name: karabo-hdf5writer
Version: 3.0.1
Summary: A simple data sink that will swallow any Karabo Data Source(s)
Author-email: "S. Hauf" <steffen.hauf@xfel.eu>
Maintainer-email: "S. Hauf" <steffen.hauf@xfel.eu>
License: Mozilla Public License Version 2.0
Classifier: Development Status :: 4 - Beta
Classifier: Intended Audience :: Developers
Classifier: Topic :: Software Development :: Build Tools
Classifier: License :: OSI Approved :: MIT License
Classifier: Programming Language :: Python :: 3.12
Classifier: Programming Language :: Python :: 3 :: Only
Requires-Python: >=3.12
License-File: LICENSE.md
Requires-Dist: h5py
Requires-Dist: karabo[karathon]
Requires-Dist: extra-data
Provides-Extra: test
Requires-Dist: pytest; extra == "test"
Requires-Dist: coverage; extra == "test"
Dynamic: license-file
